boulderopal/__init__.py
boulderopal/_configuration/__init__.py
boulderopal/_configuration/configuration.py
boulderopal/_configuration/verbosity.py
boulderopal/_constants.py
boulderopal/_core/__init__.py
boulderopal/_core/base.py
boulderopal/_core/formatter.py
boulderopal/_core/workflows.py
boulderopal/_nodes/__init__.py
boulderopal/_nodes/arithmetic_binary.py
boulderopal/_nodes/arithmetic_unary.py
boulderopal/_nodes/base.py
boulderopal/_nodes/differentiation.py
boulderopal/_nodes/filter_function.py
boulderopal/_nodes/fock_space.py
boulderopal/_nodes/infidelity.py
boulderopal/_nodes/ions.py
boulderopal/_nodes/node_data.py
boulderopal/_nodes/optimization.py
boulderopal/_nodes/oqs.py
boulderopal/_nodes/pwc.py
boulderopal/_nodes/random.py
boulderopal/_nodes/signals/__init__.py
boulderopal/_nodes/signals/signals_pwc.py
boulderopal/_nodes/signals/signals_stf.py
boulderopal/_nodes/sparse.py
boulderopal/_nodes/stf.py
boulderopal/_nodes/tensor.py
boulderopal/_nodes/utils.py
boulderopal/_nodes/validation.py
boulderopal/_typing.py
boulderopal/_utils.py
boulderopal/_validation/__init__.py
boulderopal/_validation/basic.py
boulderopal/_validation/exceptions.py
boulderopal/_validation/graph.py
boulderopal/_validation/pydantic.py
boulderopal/closed_loop/__init__.py
boulderopal/closed_loop/_optimization.py
boulderopal/closed_loop/_optimizers.py
boulderopal/cloud/__init__.py
boulderopal/cloud/_activity_monitor.py
boulderopal/cloud/_async.py
boulderopal/cloud/_authenticate.py
boulderopal/cloud/_utils.py
boulderopal/gradient_free/__init__.py
boulderopal/gradient_free/_optimization.py
boulderopal/graph/__init__.py
boulderopal/graph/_execute_graph.py
boulderopal/graph/_graph.py
boulderopal/ions/__init__.py
boulderopal/ions/_drives.py
boulderopal/ions/_ion_chain_properties.py
boulderopal/ions/_molmer_sorensen.py
boulderopal/noise_reconstruction/__init__.py
boulderopal/noise_reconstruction/_classes.py
boulderopal/noise_reconstruction/_reconstruct.py
boulderopal/optimization/__init__.py
boulder_opal-5.0.5.dist-info/LICENSE
boulder_opal-5.0.5.dist-info/METADATA
boulder_opal-5.0.5.dist-info/WHEEL
boulder_opal-5.0.5.dist-info/RECORD
