Metadata-Version: 2.3
Name: boulder-opal
Version: 5.0.5
Summary: Boulder Opal Client
License: https://q-ctrl.com/terms
Keywords: black opal,boulder opal,fire opal,nisq,open controls,q control,q ctrl,q-control,q-ctrl,qcontrol,qctrl,quantum,quantum algorithms,quantum circuits,quantum coding,quantum coding software,quantum computing,quantum control,quantum control software,quantum control theory,quantum engineering,quantum error correction,quantum firmware,quantum fundamentals,quantum sensing,qubit,qudit
Author: Q-CTRL
Author-email: support@q-ctrl.com
Maintainer: Q-CTRL
Maintainer-email: support@q-ctrl.com
Requires-Python: >=3.10,<3.13
Classifier: Development Status :: 5 - Production/Stable
Classifier: Environment :: Console
Classifier: Intended Audience :: Developers
Classifier: Intended Audience :: Education
Classifier: Intended Audience :: Science/Research
Classifier: License :: Other/Proprietary License
Classifier: Natural Language :: English
Classifier: Operating System :: OS Independent
Classifier: Programming Language :: Python :: 3
Classifier: Programming Language :: Python :: 3.10
Classifier: Programming Language :: Python :: 3.11
Classifier: Programming Language :: Python :: 3.12
Classifier: Topic :: Internet :: WWW/HTTP
Classifier: Topic :: Scientific/Engineering :: Physics
Classifier: Topic :: Scientific/Engineering :: Visualization
Classifier: Topic :: Software Development :: Embedded Systems
Classifier: Topic :: System :: Distributed Computing
Requires-Dist: numpy (>=2.0.2,<3.0.0)
Requires-Dist: pydantic (>=2.6.4,<2.12)
Requires-Dist: qctrl-client (>=14.0.0,<15.0.0)
Requires-Dist: qctrl-commons (>=25.1.3,<26.0.0)
Requires-Dist: qctrl-workflow-client (>=8.0.1,<9.0.0)
Requires-Dist: rich (>=14.1.0,<15.0.0)
Requires-Dist: typing-extensions (>=4.8.0,<5.0.0)
Project-URL: Documentation, https://docs.q-ctrl.com/boulder-opal
Project-URL: Facebook, https://www.facebook.com/qctrl
Project-URL: GitHub, https://github.com/qctrl
Project-URL: Homepage, https://q-ctrl.com
Project-URL: LinkedIn, https://www.linkedin.com/company/q-ctrl/
Project-URL: X, https://x.com/qctrlHQ
Project-URL: YouTube, https://www.youtube.com/qctrl
